oneNeuron/__init__.py
oneNeuron/perceptron.py
Perceptron_pypi_gaurav98094-0.0.3.dist-info/LICENSE
Perceptron_pypi_gaurav98094-0.0.3.dist-info/METADATA
Perceptron_pypi_gaurav98094-0.0.3.dist-info/WHEEL
Perceptron_pypi_gaurav98094-0.0.3.dist-info/top_level.txt
Perceptron_pypi_gaurav98094-0.0.3.dist-info/RECORD
